c_out/__init__.py
c_out/all_combinations.py
c_out/beauty_print.py
c_out-1.0.dist-info/LICENSE.txt
c_out-1.0.dist-info/METADATA
c_out-1.0.dist-info/WHEEL
c_out-1.0.dist-info/top_level.txt
c_out-1.0.dist-info/RECORD
