Metadata-Version: 2.1
Name: c-out
Version: 1.0
Summary: Colored Output - c_out. Python print with a style!
Home-page: https://github.com/singhgautam7/Python-GoldMine/tree/master/beauty_print
Author: Gautam Rajeev Singh
Author-email: gautamsingh1997@gmail.com
License: MIT
Keywords: pyton print color styles
Platform: UNKNOWN
Classifier: Programming Language :: Python :: 3
Classifier: License :: OSI Approved :: MIT License
Classifier: Operating System :: OS Independent
Requires-Python: >=3.0
License-File: LICENSE.txt
